<annotation>
<folder>images</folder>
<filename>J:\Main Project\Datasets\face-dataset-with-age-emotion-ethnicity\images\66127d05-93eb-498f-bac3-85a19bcbbbc7___2538464.main_image.jpg.jpeg</filename>
<path>J:\Main Project\Datasets\face-dataset-with-age-emotion-ethnicity\images\66127d05-93eb-498f-bac3-85a19bcbbbc7___2538464.main_image.jpg.jpeg</path>
<source>
	<database>Unknown</database>
</source>
<size>
	<width>1300</width>
	<height>741</height>
	<depth>Unspecified</depth>
</size>
<segmented>Unspecified</segmented>
<object>
	<name>Emotion_Happy</name>
	<pose>Unspecified</pose>
	<truncated>Unspecified</truncated>
	<difficult>Unspecified</difficult>
	<occluded>Unspecified</occluded>
	<bndbox>
		<xmin>258</xmin>
		<xmax>421</xmax>
		<ymin>171</ymin>
		<ymax>340</ymax>
	</bndbox>
</object>
<object>
	<name>Age_below20</name>
	<pose>Unspecified</pose>
	<truncated>Unspecified</truncated>
	<difficult>Unspecified</difficult>
	<occluded>Unspecified</occluded>
	<bndbox>
		<xmin>258</xmin>
		<xmax>421</xmax>
		<ymin>171</ymin>
		<ymax>340</ymax>
	</bndbox>
</object>
<object>
	<name>E_White</name>
	<pose>Unspecified</pose>
	<truncated>Unspecified</truncated>
	<difficult>Unspecified</difficult>
	<occluded>Unspecified</occluded>
	<bndbox>
		<xmin>258</xmin>
		<xmax>421</xmax>
		<ymin>171</ymin>
		<ymax>340</ymax>
	</bndbox>
</object>
<object>
	<name>G_Male</name>
	<pose>Unspecified</pose>
	<truncated>Unspecified</truncated>
	<difficult>Unspecified</difficult>
	<occluded>Unspecified</occluded>
	<bndbox>
		<xmin>258</xmin>
		<xmax>421</xmax>
		<ymin>171</ymin>
		<ymax>340</ymax>
	</bndbox>
</object>
<object>
	<name>Emotion_Happy</name>
	<pose>Unspecified</pose>
	<truncated>Unspecified</truncated>
	<difficult>Unspecified</difficult>
	<occluded>Unspecified</occluded>
	<bndbox>
		<xmin>783</xmin>
		<xmax>956</xmax>
		<ymin>118</ymin>
		<ymax>273</ymax>
	</bndbox>
</object>
<object>
	<name>Age_20_30</name>
	<pose>Unspecified</pose>
	<truncated>Unspecified</truncated>
	<difficult>Unspecified</difficult>
	<occluded>Unspecified</occluded>
	<bndbox>
		<xmin>783</xmin>
		<xmax>956</xmax>
		<ymin>118</ymin>
		<ymax>273</ymax>
	</bndbox>
</object>
<object>
	<name>E_White</name>
	<pose>Unspecified</pose>
	<truncated>Unspecified</truncated>
	<difficult>Unspecified</difficult>
	<occluded>Unspecified</occluded>
	<bndbox>
		<xmin>783</xmin>
		<xmax>956</xmax>
		<ymin>118</ymin>
		<ymax>273</ymax>
	</bndbox>
</object>
<object>
	<name>G_ Female</name>
	<pose>Unspecified</pose>
	<truncated>Unspecified</truncated>
	<difficult>Unspecified</difficult>
	<occluded>Unspecified</occluded>
	<bndbox>
		<xmin>783</xmin>
		<xmax>956</xmax>
		<ymin>118</ymin>
		<ymax>273</ymax>
	</bndbox>
</object>
</annotation>