<annotation>
<folder>images</folder>
<filename>J:\Main Project\Datasets\face-dataset-with-age-emotion-ethnicity\images\c4f62ce3-3343-4db0-b1d1-3cf4233ad928___28re15.jpg.jpeg</filename>
<path>J:\Main Project\Datasets\face-dataset-with-age-emotion-ethnicity\images\c4f62ce3-3343-4db0-b1d1-3cf4233ad928___28re15.jpg.jpeg</path>
<source>
	<database>Unknown</database>
</source>
<size>
	<width>500</width>
	<height>348</height>
	<depth>Unspecified</depth>
</size>
<segmented>Unspecified</segmented>
<object>
	<name>Emotion_Sad</name>
	<pose>Unspecified</pose>
	<truncated>Unspecified</truncated>
	<difficult>Unspecified</difficult>
	<occluded>Unspecified</occluded>
	<bndbox>
		<xmin>79</xmin>
		<xmax>130</xmax>
		<ymin>185</ymin>
		<ymax>230</ymax>
	</bndbox>
</object>
<object>
	<name>Age_20_30</name>
	<pose>Unspecified</pose>
	<truncated>Unspecified</truncated>
	<difficult>Unspecified</difficult>
	<occluded>Unspecified</occluded>
	<bndbox>
		<xmin>79</xmin>
		<xmax>130</xmax>
		<ymin>185</ymin>
		<ymax>230</ymax>
	</bndbox>
</object>
<object>
	<name>E_Indian</name>
	<pose>Unspecified</pose>
	<truncated>Unspecified</truncated>
	<difficult>Unspecified</difficult>
	<occluded>Unspecified</occluded>
	<bndbox>
		<xmin>79</xmin>
		<xmax>130</xmax>
		<ymin>185</ymin>
		<ymax>230</ymax>
	</bndbox>
</object>
<object>
	<name>G_ Female</name>
	<pose>Unspecified</pose>
	<truncated>Unspecified</truncated>
	<difficult>Unspecified</difficult>
	<occluded>Unspecified</occluded>
	<bndbox>
		<xmin>79</xmin>
		<xmax>130</xmax>
		<ymin>185</ymin>
		<ymax>230</ymax>
	</bndbox>
</object>
<object>
	<name>Emotion_Sad</name>
	<pose>Unspecified</pose>
	<truncated>Unspecified</truncated>
	<difficult>Unspecified</difficult>
	<occluded>Unspecified</occluded>
	<bndbox>
		<xmin>221</xmin>
		<xmax>251</xmax>
		<ymin>160</ymin>
		<ymax>187</ymax>
	</bndbox>
</object>
<object>
	<name>Age_20_30</name>
	<pose>Unspecified</pose>
	<truncated>Unspecified</truncated>
	<difficult>Unspecified</difficult>
	<occluded>Unspecified</occluded>
	<bndbox>
		<xmin>221</xmin>
		<xmax>251</xmax>
		<ymin>160</ymin>
		<ymax>187</ymax>
	</bndbox>
</object>
<object>
	<name>E_Indian</name>
	<pose>Unspecified</pose>
	<truncated>Unspecified</truncated>
	<difficult>Unspecified</difficult>
	<occluded>Unspecified</occluded>
	<bndbox>
		<xmin>221</xmin>
		<xmax>251</xmax>
		<ymin>160</ymin>
		<ymax>187</ymax>
	</bndbox>
</object>
<object>
	<name>G_Male</name>
	<pose>Unspecified</pose>
	<truncated>Unspecified</truncated>
	<difficult>Unspecified</difficult>
	<occluded>Unspecified</occluded>
	<bndbox>
		<xmin>221</xmin>
		<xmax>251</xmax>
		<ymin>160</ymin>
		<ymax>187</ymax>
	</bndbox>
</object>
<object>
	<name>Emotion_Neutral</name>
	<pose>Unspecified</pose>
	<truncated>Unspecified</truncated>
	<difficult>Unspecified</difficult>
	<occluded>Unspecified</occluded>
	<bndbox>
		<xmin>229</xmin>
		<xmax>257</xmax>
		<ymin>122</ymin>
		<ymax>152</ymax>
	</bndbox>
</object>
<object>
	<name>Age_20_30</name>
	<pose>Unspecified</pose>
	<truncated>Unspecified</truncated>
	<difficult>Unspecified</difficult>
	<occluded>Unspecified</occluded>
	<bndbox>
		<xmin>229</xmin>
		<xmax>257</xmax>
		<ymin>122</ymin>
		<ymax>152</ymax>
	</bndbox>
</object>
<object>
	<name>E_Indian</name>
	<pose>Unspecified</pose>
	<truncated>Unspecified</truncated>
	<difficult>Unspecified</difficult>
	<occluded>Unspecified</occluded>
	<bndbox>
		<xmin>229</xmin>
		<xmax>257</xmax>
		<ymin>122</ymin>
		<ymax>152</ymax>
	</bndbox>
</object>
<object>
	<name>G_Male</name>
	<pose>Unspecified</pose>
	<truncated>Unspecified</truncated>
	<difficult>Unspecified</difficult>
	<occluded>Unspecified</occluded>
	<bndbox>
		<xmin>229</xmin>
		<xmax>257</xmax>
		<ymin>122</ymin>
		<ymax>152</ymax>
	</bndbox>
</object>
<object>
	<name>Not_Face</name>
	<pose>Unspecified</pose>
	<truncated>Unspecified</truncated>
	<difficult>Unspecified</difficult>
	<occluded>Unspecified</occluded>
	<bndbox>
		<xmin>328</xmin>
		<xmax>355</xmax>
		<ymin>123</ymin>
		<ymax>156</ymax>
	</bndbox>
</object>
<object>
	<name>Not_Face</name>
	<pose>Unspecified</pose>
	<truncated>Unspecified</truncated>
	<difficult>Unspecified</difficult>
	<occluded>Unspecified</occluded>
	<bndbox>
		<xmin>281</xmin>
		<xmax>303</xmax>
		<ymin>125</ymin>
		<ymax>152</ymax>
	</bndbox>
</object>
<object>
	<name>Emotion_Neutral</name>
	<pose>Unspecified</pose>
	<truncated>Unspecified</truncated>
	<difficult>Unspecified</difficult>
	<occluded>Unspecified</occluded>
	<bndbox>
		<xmin>378</xmin>
		<xmax>391</xmax>
		<ymin>114</ymin>
		<ymax>133</ymax>
	</bndbox>
</object>
<object>
	<name>Age_20_30</name>
	<pose>Unspecified</pose>
	<truncated>Unspecified</truncated>
	<difficult>Unspecified</difficult>
	<occluded>Unspecified</occluded>
	<bndbox>
		<xmin>378</xmin>
		<xmax>391</xmax>
		<ymin>114</ymin>
		<ymax>133</ymax>
	</bndbox>
</object>
<object>
	<name>E_Indian</name>
	<pose>Unspecified</pose>
	<truncated>Unspecified</truncated>
	<difficult>Unspecified</difficult>
	<occluded>Unspecified</occluded>
	<bndbox>
		<xmin>378</xmin>
		<xmax>391</xmax>
		<ymin>114</ymin>
		<ymax>133</ymax>
	</bndbox>
</object>
<object>
	<name>G_Male</name>
	<pose>Unspecified</pose>
	<truncated>Unspecified</truncated>
	<difficult>Unspecified</difficult>
	<occluded>Unspecified</occluded>
	<bndbox>
		<xmin>378</xmin>
		<xmax>391</xmax>
		<ymin>114</ymin>
		<ymax>133</ymax>
	</bndbox>
</object>
<object>
	<name>Not_Face</name>
	<pose>Unspecified</pose>
	<truncated>Unspecified</truncated>
	<difficult>Unspecified</difficult>
	<occluded>Unspecified</occluded>
	<bndbox>
		<xmin>458</xmin>
		<xmax>482</xmax>
		<ymin>89</ymin>
		<ymax>120</ymax>
	</bndbox>
</object>
<object>
	<name>Not_Face</name>
	<pose>Unspecified</pose>
	<truncated>Unspecified</truncated>
	<difficult>Unspecified</difficult>
	<occluded>Unspecified</occluded>
	<bndbox>
		<xmin>396</xmin>
		<xmax>437</xmax>
		<ymin>89</ymin>
		<ymax>136</ymax>
	</bndbox>
</object>
</annotation>